kiharalab/__init__.py
kiharalab/bibtex.py
kiharalab/constants.py
kiharalab/kiharalab_logo.png
kiharalab/objects.py
kiharalab/protocols.conf
kiharalab/wizards.py
kiharalab/protocols/__init__.py
kiharalab/protocols/protocol_daq.py
kiharalab/protocols/protocol_emap2sec.py
kiharalab/protocols/protocol_mainmast_segment_map.py
kiharalab/tests/__init__.py
kiharalab/tests/test_daq.py
kiharalab/tests/test_emap2sec.py
kiharalab/tests/test_mainmastseg.py
kiharalab/utils/__init__.py
kiharalab/utils/utils.py
kiharalab/viewers/__init__.py
kiharalab/viewers/viewer_daq.py
kiharalab/viewers/viewer_emap2sec.py
kiharalab/viewers/viewer_mainmast.py
scipion_em_kiharalab-1.0.10.dist-info/LICENSE
scipion_em_kiharalab-1.0.10.dist-info/METADATA
scipion_em_kiharalab-1.0.10.dist-info/WHEEL
scipion_em_kiharalab-1.0.10.dist-info/entry_points.txt
scipion_em_kiharalab-1.0.10.dist-info/top_level.txt
scipion_em_kiharalab-1.0.10.dist-info/RECORD
