Metadata-Version: 2.1
Name: scipion-em-kiharalab
Version: 1.0.10
Summary: Scipion plugin in order to use ther kiharalab software
Home-page: https://github.com/scipion-em/scipion-em-kiharalab
Author: Daniel Del Hoyo, Martín Salinas
Author-email: ddelhoyo@cnb.csic.es, martin.salinas@cnb.csic.es
License: UNKNOWN
Project-URL: Bug Reports, https://github.com/scipion-em/scipion-em-kiharalab/issues
Project-URL: Pull Requests, https://github.com/scipion-em/scipion-em-kiharalab/pulls
Keywords: scipion kiharalab scipion-3.0 EM
Platform: UNKNOWN
Classifier: Development Status :: 4 - Beta
Classifier: License :: OSI Approved :: GNU General Public License v3 (GPLv3)
Classifier: Programming Language :: Python :: 3
Requires-Dist: scipion-em-phenix >=3.2.1
